CREDITS.md
LICENSE.txt
MANIFEST.in
README.md
setup.py
PyAllInOne/__init__.py
PyAllInOne.egg-info/PKG-INFO
PyAllInOne.egg-info/SOURCES.txt
PyAllInOne.egg-info/dependency_links.txt
PyAllInOne.egg-info/requires.txt
PyAllInOne.egg-info/top_level.txt
PyAllInOne/English/Grammar.py
PyAllInOne/English/Words.py
PyAllInOne/English/__init__.py
PyAllInOne/English/assets/dictionary.json
PyAllInOne/Files/JSON.py
PyAllInOne/Files/__init__.py
PyAllInOne/Jokes/__init__.py
PyAllInOne/Math/Arithmetic.py
PyAllInOne/Math/Geometry.py
PyAllInOne/Math/Graphs.py
PyAllInOne/Math/Quadratic.py
PyAllInOne/Math/Statistics.py
PyAllInOne/Math/Trigonometry.py
PyAllInOne/Math/__init__.py
PyAllInOne/Speech/TextToSpeech.py
PyAllInOne/Speech/__init__.py
PyAllInOne/System/Brightness.py
PyAllInOne/System/Clipboard.py
PyAllInOne/System/Info.py
PyAllInOne/System/Volume.py
PyAllInOne/System/__init__.py
PyAllInOne/System/assets/SetVol.exe
PyAllInOne/Traffic/LicensePlate.py
PyAllInOne/Traffic/PeopleDetection.py
PyAllInOne/Traffic/VehicleDetection.py
PyAllInOne/Traffic/__init__.py
PyAllInOne/Traffic/assets/models/haarcascade_car.xml
PyAllInOne/Traffic/assets/models/haarcascade_russian_plate_number.xml
PyAllInOne/Traffic/assets/sample_media/LicensePlate/images/1.jpg
PyAllInOne/Traffic/assets/sample_media/LicensePlate/images/2.jpg
PyAllInOne/Traffic/assets/sample_media/LicensePlate/images/3.jpg
PyAllInOne/Traffic/assets/sample_media/LicensePlate/images/4.jpg
PyAllInOne/Traffic/assets/sample_media/LicensePlate/images/5.jpg
PyAllInOne/Traffic/assets/sample_media/LicensePlate/images/6.jpg
PyAllInOne/Traffic/assets/sample_media/LicensePlate/images/7.jpg
PyAllInOne/Traffic/assets/sample_media/LicensePlate/images/8.jpg
PyAllInOne/Traffic/assets/sample_media/PeopleDetection/videos/1.mp4
PyAllInOne/Traffic/assets/sample_media/PeopleDetection/videos/2.mp4
PyAllInOne/Traffic/assets/sample_media/PeopleDetection/videos/3.mp4
PyAllInOne/Traffic/assets/sample_media/PeopleDetection/videos/4.mp4
PyAllInOne/Traffic/assets/sample_media/PeopleDetection/videos/5.mp4
PyAllInOne/Traffic/assets/sample_media/VehicleDetection/images/1.jpg
