Metadata-Version: 2.1
Name: PyAllInOne
Version: 1.0.7
Summary: PyAllInOne is an advanced multi-purpose Python package.
Home-page: https://github.com/Anikethc/PyAllInOne
Download-URL: https://pypi.org/project/PyAllInOne
Author: Aniketh Chavare
Author-email: anikethchavare@outlook.com
License: Apache License 2.0
Classifier: Development Status :: 5 - Production/Stable
Classifier: License :: OSI Approved :: Apache Software License
Classifier: Natural Language :: English
Classifier: Operating System :: Microsoft :: Windows
Classifier: Operating System :: MacOS
Classifier: Operating System :: Unix
Classifier: Programming Language :: Python
Classifier: Programming Language :: Python :: 3
Classifier: Topic :: Software Development
License-File: LICENSE.txt
